pyqt_rounded_profile_image/__init__.py
pyqt_rounded_profile_image/main.py
pyqt_rounded_profile_image-0.0.1.dist-info/LICENSE
pyqt_rounded_profile_image-0.0.1.dist-info/METADATA
pyqt_rounded_profile_image-0.0.1.dist-info/WHEEL
pyqt_rounded_profile_image-0.0.1.dist-info/top_level.txt
pyqt_rounded_profile_image-0.0.1.dist-info/RECORD
