Metadata-Version: 2.1
Name: pyqt-rounded-profile-image
Version: 0.0.1
Summary: PyQt rounded profile image
Home-page: https://github.com/yjg30737/pyqt-rounded-profile-image.git
Author: Jung Gyu Yoon
Author-email: yjg30737@gmail.com
License: MIT
Platform: UNKNOWN
License-File: LICENSE
Requires-Dist: PyQt5
